dummy_ERG/__init__.py
dummy_erg-3.14.0.dist-info/LICENSE
dummy_erg-3.14.0.dist-info/METADATA
dummy_erg-3.14.0.dist-info/WHEEL
dummy_erg-3.14.0.dist-info/RECORD
